moon/__init__.py
moon/_types.py
moon/formats.py
moon/logger.py
moonlogger-0.9.5.dist-info/METADATA
moonlogger-0.9.5.dist-info/WHEEL
moonlogger-0.9.5.dist-info/top_level.txt
moonlogger-0.9.5.dist-info/RECORD
