Metadata-Version: 2.1
Name: moonlogger
Version: 0.9.5
Summary: moon-logger, a Python logging library
Home-page: https://github.com/reslaid/moon
Author: Artem Reslaid
License: MIT License
Platform: UNKNOWN
Classifier: Development Status :: 3 - Alpha
Classifier: Intended Audience :: Developers
Classifier: License :: OSI Approved :: MIT License
Classifier: Programming Language :: Python :: 3.7
Classifier: Programming Language :: Python :: 3.8
Classifier: Programming Language :: Python :: 3.9
Classifier: Programming Language :: Python :: 3.10
Classifier: Programming Language :: Python :: 3.11
Classifier: Programming Language :: Python :: 3.12
Requires-Dist: PyYAML
Requires-Dist: avro
Requires-Dist: prettytable
Requires-Dist: protobuf
